{
  "experiment_name": "oracle_ptn_5_notFramed",
  "parameters": {
    "experiment_name": "oracle_ptn_5_notFramed",
    "lr": 0.0001,
    "device": "cuda",
    "seed": 1337,
    "desired_classes_source": [
      "3123D52",
      "3123D65",
      "3123D79",
      "3123D80",
      "3123D54",
      "3123D70",
      "3123D7B",
      "3123D89",
      "3123D58",
      "3123D76",
      "3123D7D",
      "3123EFE",
      "3123D64",
      "3123D78",
      "3123D7E",
      "3124E4A"
    ],
    "desired_classes_target": [
      "3123D52",
      "3123D65",
      "3123D79",
      "3123D80",
      "3123D54",
      "3123D70",
      "3123D7B",
      "3123D89",
      "3123D58",
      "3123D76",
      "3123D7D",
      "3123EFE",
      "3123D64",
      "3123D78",
      "3123D7E",
      "3124E4A"
    ],
    "num_examples_per_class_per_domain_source": 1367,
    "num_examples_per_class_per_domain_target": 1367,
    "n_shot": 3,
    "n_way": 16,
    "n_query": 2,
    "train_k_factor": 1,
    "val_k_factor": 2,
    "test_k_factor": 2,
    "n_epoch": 100,
    "patience": 10,
    "criteria_for_best": "source",
    "normalize_source": false,
    "normalize_target": false,
    "x_net": [
      {
        "class": "nnReshape",
        "kargs": {
          "shape": [
            -1,
            1,
            2,
            256
          ]
        }
      },
      {
        "class": "Conv2d",
        "kargs": {
          "in_channels": 1,
          "out_channels": 256,
          "kernel_size": [
            1,
            7
          ],
          "bias": false,
          "padding": [
            0,
            3
          ]
        }
      },
      {
        "class": "ReLU",
        "kargs": {
          "inplace": true
        }
      },
      {
        "class": "BatchNorm2d",
        "kargs": {
          "num_features": 256
        }
      },
      {
        "class": "Conv2d",
        "kargs": {
          "in_channels": 256,
          "out_channels": 80,
          "kernel_size": [
            2,
            7
          ],
          "bias": true,
          "padding": [
            0,
            3
          ]
        }
      },
      {
        "class": "ReLU",
        "kargs": {
          "inplace": true
        }
      },
      {
        "class": "BatchNorm2d",
        "kargs": {
          "num_features": 80
        }
      },
      {
        "class": "Flatten",
        "kargs": {}
      },
      {
        "class": "Linear",
        "kargs": {
          "in_features": 20480,
          "out_features": 256
        }
      },
      {
        "class": "ReLU",
        "kargs": {
          "inplace": true
        }
      },
      {
        "class": "BatchNorm1d",
        "kargs": {
          "num_features": 256
        }
      },
      {
        "class": "Linear",
        "kargs": {
          "in_features": 256,
          "out_features": 256
        }
      }
    ],
    "NUM_LOGS_PER_EPOCH": 10,
    "RESULTS_DIR": "./results",
    "EXPERIMENT_JSON_PATH": "./results/experiment.json",
    "LOSS_CURVE_PATH": "./results/loss.png",
    "BEST_MODEL_PATH": "./results/best_model.pth",
    "source_domains": [
      44
    ],
    "target_domains": [
      8,
      14,
      20,
      26,
      32,
      38,
      50,
      56
    ],
    "dataset_path": "/mnt/wd500GB/CSC500/csc500-super-repo/datasets/oracle.stratified_ds.2022A.pkl"
  },
  "results": {
    "source_test_label_accuracy": 0.7168445121951219,
    "source_test_label_loss": 0.7376967645669968,
    "target_test_label_accuracy": 0.556640625,
    "target_test_label_loss": 2.403665440480305,
    "source_val_label_accuracy": 0.6993140243902439,
    "source_val_label_loss": 0.7871819866733837,
    "target_val_label_accuracy": 0.5628334603658537,
    "target_val_label_loss": 2.3531537635404836,
    "total_epochs_trained": 20,
    "total_experiment_time_secs": 4240.736639261246,
    "confusion": {
      "44": {
        "11": {
          "11": 163,
          "13": 1
        },
        "15": {
          "15": 93,
          "5": 25,
          "14": 21,
          "8": 15,
          "0": 8,
          "4": 2
        },
        "3": {
          "3": 129,
          "12": 35
        },
        "12": {
          "12": 142,
          "3": 22
        },
        "9": {
          "7": 62,
          "6": 19,
          "4": 3,
          "2": 5,
          "9": 56,
          "13": 14,
          "10": 4,
          "14": 1
        },
        "8": {
          "8": 87,
          "0": 50,
          "15": 15,
          "5": 11,
          "14": 1
        },
        "13": {
          "13": 124,
          "6": 34,
          "11": 1,
          "9": 5
        },
        "1": {
          "1": 134,
          "2": 30
        },
        "14": {
          "14": 99,
          "4": 43,
          "5": 13,
          "15": 9
        },
        "0": {
          "8": 42,
          "0": 119,
          "15": 3
        },
        "2": {
          "2": 134,
          "10": 12,
          "1": 15,
          "7": 3
        },
        "10": {
          "10": 135,
          "7": 19,
          "2": 8,
          "1": 2
        },
        "7": {
          "7": 112,
          "9": 36,
          "6": 1,
          "10": 15
        },
        "6": {
          "6": 97,
          "13": 43,
          "9": 23,
          "7": 1
        },
        "4": {
          "14": 60,
          "4": 89,
          "9": 3,
          "15": 6,
          "5": 4,
          "13": 2
        },
        "5": {
          "5": 122,
          "15": 19,
          "14": 17,
          "4": 4,
          "8": 2
        }
      },
      "32": {
        "15": {
          "15": 149,
          "5": 13,
          "7": 1,
          "14": 1
        },
        "3": {
          "3": 137,
          "4": 9,
          "13": 18
        },
        "6": {
          "6": 158,
          "10": 6
        },
        "1": {
          "1": 164
        },
        "8": {
          "8": 34,
          "7": 32,
          "0": 17,
          "14": 42,
          "5": 29,
          "2": 7,
          "4": 3
        },
        "10": {
          "10": 158,
          "12": 5,
          "6": 1
        },
        "9": {
          "2": 9,
          "9": 129,
          "12": 22,
          "4": 3,
          "13": 1
        },
        "13": {
          "3": 33,
          "13": 96,
          "4": 24,
          "11": 9,
          "2": 2
        },
        "12": {
          "12": 146,
          "9": 16,
          "10": 2
        },
        "5": {
          "7": 38,
          "5": 70,
          "0": 13,
          "15": 22,
          "8": 13,
          "14": 8
        },
        "0": {
          "14": 27,
          "0": 74,
          "5": 8,
          "7": 43,
          "8": 12
        },
        "2": {
          "2": 108,
          "4": 48,
          "14": 6,
          "13": 1,
          "8": 1
        },
        "11": {
          "11": 159,
          "3": 1,
          "13": 4
        },
        "14": {
          "8": 34,
          "14": 49,
          "0": 25,
          "7": 31,
          "4": 3,
          "2": 9,
          "5": 13
        },
        "7": {
          "7": 39,
          "5": 40,
          "0": 37,
          "14": 20,
          "8": 28
        },
        "4": {
          "2": 55,
          "4": 84,
          "13": 15,
          "3": 7,
          "8": 2,
          "14": 1
        }
      },
      "50": {
        "3": {
          "3": 164
        },
        "15": {
          "4": 7,
          "9": 19,
          "6": 25,
          "15": 104,
          "12": 4,
          "5": 3,
          "11": 2
        },
        "8": {
          "8": 151,
          "10": 11,
          "13": 2
        },
        "4": {
          "4": 116,
          "7": 24,
          "5": 9,
          "15": 13,
          "6": 2
        },
        "14": {
          "2": 13,
          "14": 150,
          "0": 1
        },
        "0": {
          "0": 113,
          "2": 36,
          "10": 11,
          "14": 4
        },
        "7": {
          "7": 131,
          "4": 14,
          "5": 19
        },
        "6": {
          "6": 113,
          "15": 25,
          "5": 25,
          "11": 1
        },
        "10": {
          "10": 133,
          "8": 16,
          "0": 14,
          "1": 1
        },
        "5": {
          "5": 62,
          "6": 27,
          "7": 43,
          "15": 6,
          "13": 9,
          "4": 13,
          "11": 1,
          "3": 1,
          "1": 2
        },
        "2": {
          "2": 114,
          "0": 40,
          "14": 10
        },
        "12": {
          "12": 77,
          "11": 73,
          "9": 12,
          "15": 1,
          "6": 1
        },
        "9": {
          "9": 122,
          "15": 15,
          "11": 9,
          "12": 18
        },
        "1": {
          "1": 132,
          "10": 4,
          "13": 24,
          "12": 2,
          "11": 2
        },
        "11": {
          "12": 82,
          "11": 60,
          "9": 19,
          "13": 1,
          "1": 1,
          "6": 1
        },
        "13": {
          "13": 154,
          "1": 7,
          "5": 2,
          "6": 1
        }
      },
      "14": {
        "5": {
          "5": 60,
          "2": 53,
          "4": 10,
          "7": 21,
          "0": 4,
          "8": 8,
          "13": 1,
          "14": 6,
          "10": 1
        },
        "8": {
          "8": 107,
          "5": 11,
          "12": 13,
          "2": 5,
          "14": 3,
          "4": 14,
          "10": 4,
          "0": 5,
          "3": 2
        },
        "11": {
          "11": 157,
          "1": 4,
          "9": 2,
          "0": 1
        },
        "1": {
          "1": 143,
          "9": 3,
          "10": 5,
          "4": 2,
          "0": 11
        },
        "10": {
          "1": 5,
          "10": 96,
          "4": 32,
          "0": 22,
          "9": 2,
          "8": 5,
          "12": 2
        },
        "15": {
          "15": 164
        },
        "3": {
          "14": 38,
          "13": 25,
          "3": 71,
          "0": 3,
          "6": 20,
          "2": 4,
          "7": 3
        },
        "7": {
          "13": 10,
          "5": 15,
          "2": 18,
          "14": 22,
          "7": 82,
          "6": 6,
          "3": 9,
          "0": 2
        },
        "4": {
          "4": 98,
          "10": 32,
          "8": 12,
          "2": 3,
          "5": 12,
          "1": 2,
          "0": 5
        },
        "14": {
          "14": 43,
          "7": 34,
          "6": 6,
          "3": 29,
          "2": 17,
          "5": 19,
          "13": 11,
          "8": 1,
          "0": 4
        },
        "9": {
          "9": 131,
          "10": 14,
          "12": 1,
          "0": 12,
          "1": 6
        },
        "12": {
          "12": 152,
          "8": 10,
          "0": 1,
          "10": 1
        },
        "6": {
          "3": 18,
          "6": 65,
          "7": 10,
          "13": 51,
          "2": 3,
          "14": 14,
          "0": 3
        },
        "2": {
          "4": 18,
          "8": 14,
          "5": 51,
          "3": 5,
          "2": 25,
          "6": 6,
          "7": 20,
          "14": 17,
          "10": 1,
          "13": 6,
          "0": 1
        },
        "0": {
          "1": 32,
          "5": 2,
          "14": 9,
          "15": 16,
          "9": 37,
          "7": 6,
          "4": 4,
          "10": 9,
          "13": 6,
          "6": 6,
          "0": 16,
          "3": 4,
          "2": 4,
          "11": 3,
          "12": 6,
          "8": 4
        },
        "13": {
          "0": 5,
          "13": 31,
          "14": 15,
          "6": 38,
          "7": 25,
          "2": 9,
          "3": 14,
          "15": 13,
          "5": 12,
          "4": 1,
          "8": 1
        }
      },
      "20": {
        "9": {
          "15": 12,
          "4": 10,
          "5": 16,
          "12": 10,
          "8": 9,
          "3": 17,
          "2": 14,
          "9": 21,
          "7": 17,
          "1": 19,
          "14": 4,
          "6": 12,
          "0": 1,
          "10": 1,
          "13": 1
        },
        "10": {
          "6": 12,
          "10": 85,
          "4": 17,
          "13": 30,
          "2": 6,
          "12": 9,
          "9": 2,
          "7": 1,
          "15": 2
        },
        "13": {
          "13": 78,
          "12": 19,
          "4": 8,
          "15": 14,
          "10": 21,
          "2": 15,
          "7": 5,
          "9": 2,
          "6": 2
        },
        "0": {
          "8": 28,
          "11": 41,
          "0": 84,
          "3": 3,
          "5": 2,
          "14": 5,
          "1": 1
        },
        "1": {
          "9": 22,
          "5": 28,
          "12": 13,
          "1": 32,
          "8": 11,
          "4": 4,
          "7": 7,
          "6": 2,
          "15": 19,
          "3": 15,
          "2": 7,
          "14": 4
        },
        "15": {
          "12": 17,
          "15": 39,
          "13": 20,
          "7": 9,
          "4": 21,
          "5": 9,
          "2": 11,
          "6": 6,
          "9": 6,
          "1": 20,
          "3": 2,
          "10": 3,
          "14": 1
        },
        "5": {
          "5": 39,
          "14": 8,
          "9": 18,
          "1": 25,
          "3": 30,
          "12": 7,
          "4": 4,
          "8": 16,
          "2": 5,
          "0": 3,
          "7": 3,
          "6": 1,
          "15": 5
        },
        "3": {
          "0": 5,
          "5": 33,
          "8": 25,
          "4": 4,
          "1": 16,
          "9": 23,
          "3": 29,
          "6": 4,
          "14": 14,
          "7": 4,
          "2": 2,
          "15": 3,
          "12": 2
        },
        "6": {
          "6": 61,
          "9": 6,
          "7": 23,
          "13": 3,
          "8": 6,
          "10": 14,
          "2": 11,
          "14": 12,
          "4": 6,
          "12": 5,
          "15": 1,
          "5": 3,
          "3": 9,
          "1": 4
        },
        "11": {
          "0": 30,
          "8": 11,
          "11": 117,
          "14": 4,
          "5": 2
        },
        "8": {
          "8": 55,
          "14": 41,
          "0": 12,
          "3": 25,
          "11": 10,
          "4": 2,
          "5": 12,
          "9": 5,
          "1": 1,
          "7": 1
        },
        "4": {
          "7": 21,
          "2": 21,
          "9": 8,
          "15": 14,
          "12": 21,
          "1": 6,
          "6": 14,
          "4": 22,
          "13": 20,
          "3": 2,
          "5": 1,
          "10": 13,
          "14": 1
        },
        "12": {
          "13": 27,
          "5": 5,
          "15": 23,
          "1": 9,
          "7": 14,
          "12": 17,
          "6": 4,
          "2": 24,
          "4": 18,
          "9": 8,
          "10": 10,
          "3": 5
        },
        "14": {
          "8": 48,
          "14": 70,
          "7": 3,
          "3": 15,
          "2": 1,
          "6": 8,
          "9": 7,
          "11": 4,
          "5": 3,
          "1": 2,
          "4": 1,
          "0": 2
        },
        "2": {
          "2": 20,
          "15": 16,
          "13": 15,
          "5": 4,
          "12": 11,
          "3": 3,
          "10": 13,
          "1": 12,
          "14": 1,
          "7": 25,
          "9": 10,
          "4": 20,
          "6": 13,
          "8": 1
        },
        "7": {
          "7": 34,
          "6": 27,
          "1": 10,
          "4": 18,
          "2": 19,
          "12": 13,
          "14": 9,
          "9": 9,
          "15": 9,
          "3": 7,
          "10": 4,
          "8": 1,
          "5": 3,
          "13": 1
        }
      },
      "38": {
        "7": {
          "0": 3,
          "7": 153,
          "13": 2,
          "4": 1,
          "9": 5
        },
        "3": {
          "3": 164
        },
        "8": {
          "8": 54,
          "5": 49,
          "12": 33,
          "7": 13,
          "15": 5,
          "9": 6,
          "2": 1,
          "14": 3
        },
        "2": {
          "2": 130,
          "14": 34
        },
        "14": {
          "13": 17,
          "2": 66,
          "14": 80,
          "0": 1
        },
        "4": {
          "4": 109,
          "0": 33,
          "10": 21,
          "13": 1
        },
        "6": {
          "6": 156,
          "1": 8
        },
        "15": {
          "15": 140,
          "8": 5,
          "5": 9,
          "1": 6,
          "12": 3,
          "2": 1
        },
        "10": {
          "4": 14,
          "10": 137,
          "13": 7,
          "3": 2,
          "0": 4
        },
        "11": {
          "11": 164
        },
        "13": {
          "13": 120,
          "14": 29,
          "0": 4,
          "10": 7,
          "4": 3,
          "2": 1
        },
        "9": {
          "9": 111,
          "7": 11,
          "12": 10,
          "8": 17,
          "5": 15
        },
        "0": {
          "0": 49,
          "7": 18,
          "4": 45,
          "3": 19,
          "10": 18,
          "14": 2,
          "8": 2,
          "5": 1,
          "13": 10
        },
        "1": {
          "1": 149,
          "6": 14,
          "15": 1
        },
        "12": {
          "5": 40,
          "2": 1,
          "12": 74,
          "8": 34,
          "9": 12,
          "7": 2,
          "14": 1
        },
        "5": {
          "14": 3,
          "8": 48,
          "12": 43,
          "9": 34,
          "15": 7,
          "5": 25,
          "7": 3,
          "2": 1
        }
      },
      "8": {
        "8": {
          "4": 31,
          "8": 66,
          "11": 18,
          "7": 12,
          "13": 5,
          "14": 11,
          "6": 16,
          "5": 2,
          "10": 3
        },
        "14": {
          "14": 120,
          "4": 32,
          "0": 3,
          "11": 5,
          "8": 4
        },
        "2": {
          "2": 62,
          "3": 35,
          "15": 46,
          "12": 21
        },
        "0": {
          "0": 164
        },
        "1": {
          "1": 29,
          "8": 8,
          "7": 13,
          "4": 11,
          "6": 17,
          "13": 15,
          "5": 18,
          "11": 28,
          "10": 25
        },
        "10": {
          "10": 21,
          "6": 16,
          "5": 32,
          "1": 25,
          "11": 24,
          "13": 25,
          "7": 12,
          "8": 5,
          "4": 4
        },
        "11": {
          "10": 14,
          "8": 17,
          "5": 12,
          "1": 23,
          "11": 28,
          "6": 20,
          "13": 11,
          "4": 24,
          "7": 9,
          "14": 6
        },
        "5": {
          "13": 29,
          "10": 30,
          "11": 8,
          "1": 18,
          "5": 57,
          "8": 1,
          "6": 9,
          "7": 5,
          "4": 5,
          "12": 2
        },
        "15": {
          "2": 47,
          "12": 49,
          "15": 65,
          "3": 3
        },
        "3": {
          "3": 161,
          "2": 2,
          "15": 1
        },
        "12": {
          "15": 42,
          "12": 102,
          "2": 20
        },
        "7": {
          "1": 12,
          "8": 9,
          "13": 26,
          "5": 13,
          "7": 48,
          "6": 22,
          "11": 16,
          "10": 16,
          "4": 2
        },
        "13": {
          "13": 31,
          "7": 19,
          "1": 24,
          "5": 37,
          "6": 16,
          "10": 23,
          "11": 10,
          "4": 2,
          "8": 2
        },
        "6": {
          "6": 36,
          "10": 10,
          "13": 9,
          "7": 33,
          "8": 29,
          "11": 18,
          "14": 1,
          "5": 4,
          "4": 4,
          "1": 20
        },
        "4": {
          "4": 62,
          "8": 35,
          "11": 19,
          "6": 6,
          "14": 25,
          "1": 7,
          "7": 3,
          "10": 4,
          "5": 3
        },
        "9": {
          "9": 164
        }
      },
      "56": {
        "4": {
          "3": 35,
          "4": 63,
          "2": 58,
          "6": 3,
          "13": 5
        },
        "12": {
          "12": 95,
          "1": 58,
          "15": 9,
          "10": 2
        },
        "10": {
          "5": 65,
          "10": 81,
          "1": 1,
          "0": 11,
          "12": 5,
          "7": 1
        },
        "0": {
          "0": 151,
          "7": 1,
          "10": 7,
          "9": 2,
          "5": 3
        },
        "13": {
          "13": 131,
          "6": 22,
          "2": 3,
          "7": 8
        },
        "9": {
          "9": 135,
          "6": 4,
          "5": 3,
          "0": 18,
          "10": 4
        },
        "3": {
          "3": 151,
          "4": 13
        },
        "2": {
          "2": 124,
          "4": 39,
          "3": 1
        },
        "5": {
          "10": 54,
          "5": 83,
          "1": 6,
          "8": 17,
          "12": 4
        },
        "14": {
          "14": 128,
          "7": 36
        },
        "8": {
          "8": 116,
          "12": 5,
          "5": 18,
          "15": 9,
          "1": 14,
          "10": 2
        },
        "7": {
          "7": 114,
          "14": 49,
          "13": 1
        },
        "6": {
          "4": 7,
          "13": 24,
          "6": 119,
          "2": 5,
          "9": 4,
          "0": 4,
          "7": 1
        },
        "11": {
          "11": 164
        },
        "15": {
          "15": 94,
          "1": 43,
          "12": 13,
          "8": 13,
          "5": 1
        },
        "1": {
          "1": 77,
          "15": 29,
          "12": 48,
          "5": 3,
          "8": 4,
          "10": 3
        }
      },
      "26": {
        "12": {
          "12": 136,
          "9": 11,
          "13": 9,
          "8": 6,
          "7": 2
        },
        "7": {
          "2": 37,
          "9": 22,
          "0": 2,
          "7": 49,
          "3": 18,
          "8": 34,
          "13": 2
        },
        "5": {
          "15": 31,
          "5": 40,
          "10": 18,
          "6": 27,
          "1": 25,
          "11": 1,
          "14": 22
        },
        "15": {
          "14": 28,
          "10": 19,
          "0": 21,
          "1": 8,
          "15": 32,
          "5": 26,
          "6": 30
        },
        "8": {
          "2": 44,
          "9": 28,
          "7": 21,
          "8": 43,
          "3": 12,
          "0": 12,
          "12": 2,
          "13": 1,
          "14": 1
        },
        "2": {
          "8": 33,
          "9": 15,
          "0": 20,
          "3": 17,
          "7": 35,
          "2": 40,
          "15": 1,
          "10": 3
        },
        "13": {
          "13": 74,
          "4": 39,
          "8": 3,
          "9": 16,
          "3": 13,
          "12": 12,
          "2": 3,
          "7": 4
        },
        "4": {
          "4": 126,
          "13": 23,
          "3": 14,
          "7": 1
        },
        "0": {
          "0": 59,
          "2": 16,
          "15": 12,
          "10": 27,
          "8": 9,
          "6": 10,
          "9": 4,
          "14": 18,
          "1": 2,
          "5": 7
        },
        "6": {
          "15": 30,
          "5": 43,
          "6": 47,
          "10": 13,
          "14": 12,
          "11": 3,
          "1": 15,
          "0": 1
        },
        "9": {
          "3": 24,
          "8": 32,
          "9": 40,
          "7": 17,
          "2": 21,
          "13": 13,
          "10": 1,
          "12": 8,
          "4": 1,
          "0": 7
        },
        "11": {
          "1": 3,
          "11": 147,
          "5": 4,
          "6": 6,
          "10": 2,
          "15": 2
        },
        "10": {
          "14": 31,
          "0": 22,
          "5": 24,
          "10": 41,
          "6": 14,
          "15": 26,
          "11": 1,
          "1": 4,
          "7": 1
        },
        "14": {
          "14": 43,
          "10": 23,
          "15": 32,
          "6": 17,
          "0": 20,
          "1": 9,
          "5": 20
        },
        "1": {
          "10": 6,
          "5": 24,
          "14": 10,
          "1": 89,
          "6": 21,
          "15": 10,
          "11": 1,
          "0": 3
        },
        "3": {
          "7": 28,
          "8": 11,
          "3": 58,
          "13": 19,
          "9": 26,
          "2": 13,
          "4": 8,
          "12": 1
        }
      }
    },
    "per_domain_accuracy": {
      "44": {
        "accuracy": 0.6993140243902439,
        "source?": true
      },
      "32": {
        "accuracy": 0.6684451219512195,
        "source?": false
      },
      "50": {
        "accuracy": 0.7225609756097561,
        "source?": false
      },
      "14": {
        "accuracy": 0.5491615853658537,
        "source?": false
      },
      "20": {
        "accuracy": 0.30602134146341464,
        "source?": false
      },
      "38": {
        "accuracy": 0.6916920731707317,
        "source?": false
      },
      "8": {
        "accuracy": 0.4634146341463415,
        "source?": false
      },
      "56": {
        "accuracy": 0.6958841463414634,
        "source?": false
      },
      "26": {
        "accuracy": 0.4054878048780488,
        "source?": false
      }
    }
  },
  "history": {
    "epoch_indices": [
      1,
      2,
      3,
      4,
      5,
      6,
      7,
      8,
      9,
      10,
      11,
      12,
      13,
      14,
      15,
      16,
      17,
      18,
      19,
      20
    ],
    "train_label_loss": [
      1.4625026425080163,
      1.3371462843508182,
      1.2946454268791654,
      1.2582303995324122,
      1.0191202656316356,
      0.7259359542259014,
      0.6110667119106459,
      0.5145711288492526,
      0.45107033522878454,
      0.3601183385071291,
      0.32163151533600326,
      0.25210096407801674,
      0.1970871630373017,
      0.17946861406768527,
      0.14672110809900862,
      0.1326801893238022,
      0.11462120259821977,
      0.0890294454969156,
      0.09242460544432418,
      0.09761271702086467
    ],
    "source_val_label_loss": [
      1.4085940703053574,
      1.389601787074632,
      1.3767355218244963,
      1.3800276093519015,
      0.9407472543580009,
      0.8334671553007515,
      0.7876280621883914,
      0.8006292683820008,
      0.7871819866733837,
      0.8532950675238421,
      0.8592331348435505,
      0.8711442189192907,
      0.8828986022686647,
      0.951011264289706,
      0.9810572712913072,
      0.9691181522395589,
      1.0226222113467376,
      1.0328890660794574,
      1.086937885931907,
      1.0724226610186096
    ],
    "target_val_label_loss": [
      2.0089089525468866,
      2.1412188645870356,
      2.1868220521577135,
      2.4010164793990527,
      1.9973288273074161,
      2.0638762152574786,
      2.1043697519578606,
      2.3887739823194547,
      2.3531537635404836,
      2.8662070872473224,
      3.219756876858545,
      3.327734122705171,
      3.4410755663333923,
      3.5466714182300825,
      4.246902087233504,
      4.088347663134317,
      4.472895468335839,
      4.549297550524176,
      4.896320511828285,
      4.637974989580529
    ],
    "source_val_acc_label": [
      0.4367378048780488,
      0.43902439024390244,
      0.4420731707317073,
      0.4504573170731707,
      0.6154725609756098,
      0.6676829268292683,
      0.6890243902439024,
      0.6947408536585366,
      0.6993140243902439,
      0.6897865853658537,
      0.7130335365853658,
      0.6996951219512195,
      0.7076981707317073,
      0.692454268292683,
      0.7069359756097561,
      0.7191310975609756,
      0.7130335365853658,
      0.7191310975609756,
      0.7126524390243902,
      0.7008384146341463
    ],
    "target_val_acc_label": [
      0.40072408536585363,
      0.3942454268292683,
      0.3971512957317073,
      0.3958174542682927,
      0.5086699695121951,
      0.5484946646341463,
      0.555640243902439,
      0.5609756097560976,
      0.5628334603658537,
      0.5603563262195121,
      0.5580697408536586,
      0.5558307926829268,
      0.5569740853658537,
      0.5513528963414634,
      0.5562118902439024,
      0.5574028201219512,
      0.5570217225609756,
      0.5603563262195121,
      0.5564024390243902,
      0.5481135670731707
    ]
  },
  "dataset_metrics": {
    "source": {
      "train": {
        "n_unique_x": 15280,
        "n_unique_y": 16,
        "n_batch/episode": 191
      },
      "val": {
        "n_unique_x": 3280,
        "n_unique_y": 16,
        "n_batch/episode": 82
      },
      "test": {
        "n_unique_x": 3296,
        "n_unique_y": 16,
        "n_batch/episode": 82
      }
    },
    "target": {
      "train": {
        "n_unique_x": 122240,
        "n_unique_y": 16,
        "n_batch/episode": 1528
      },
      "val": {
        "n_unique_x": 26240,
        "n_unique_y": 16,
        "n_batch/episode": 656
      },
      "test": {
        "n_unique_x": 26368,
        "n_unique_y": 16,
        "n_batch/episode": 656
      }
    }
  },
  "super_repo_commit": "8d7b87bf668336f72d95bfbab4a13134af4eae42"
}